facemask_detection/__init__.py
facemask_detection/dataloader.py
facemask_detection/inference.py
facemask_detection/pre_trained_models.py
facemask_detection/train.py
facemask_detection/utils.py
facemask_detection-0.0.4.dist-info/LICENSE
facemask_detection-0.0.4.dist-info/METADATA
facemask_detection-0.0.4.dist-info/WHEEL
facemask_detection-0.0.4.dist-info/top_level.txt
facemask_detection-0.0.4.dist-info/RECORD
