Metadata-Version: 2.1
Name: facemask-detection
Version: 0.0.4
Summary: Unstructured set of the helper functions.
Home-page: https://github.com/ternaus/facemask_detection
Author: Vladimir Iglovikov
License: MIT
Platform: UNKNOWN
Classifier: License :: OSI Approved :: MIT License
Classifier: Intended Audience :: Developers
Classifier: Intended Audience :: Science/Research
Classifier: Operating System :: OS Independent
Classifier: Programming Language :: Python
Classifier: Programming Language :: Python :: 3
Classifier: Topic :: Software Development :: Libraries
Classifier: Topic :: Software Development :: Libraries :: Python Modules
Requires-Dist: albumentations
Requires-Dist: timm
Provides-Extra: test
Requires-Dist: pytest ; extra == 'test'
